Workbook

Sheet StoreData
A1: Month | B1: Electronics | C1: HomeGoods | D1: Clothing | E1: Elec_Expenses | F1: Home_Expenses | G1: Cloth_Expenses
A2: January | B2: 120000 | C2: 85000 | D2: 60000 | E2: 70000 | F2: 40000 | G2: 30000
A3: February | B3: 135000 | C3: 90000 | D3: 65000 | E3: 75000 | F3: 42000 | G3: 31000
A4: March | B4: 150000 | C4: 95000 | D4: 70000 | E4: 82000 | F4: 45000 | G4: 33000
A5: April | B5: 160000 | C5: 100000 | D5: 72000 | E5: 88000 | F5: 47000 | G5: 34000
A6: May | B6: 170000 | C6: 99000 | D6: 75000 | E6: 92000 | F6: 46000 | G6: 35000
A7: June | B7: 155000 | C7: 97000 | D7: 77000 | E7: 83000 | F7: 45500 | G7: 36000

Sheet 2.2.1_Managers_Report
A1: Manager's Summary Report — Total 6-Month Sales by Category
A3: Product Category | B3: Total Sales (6 Months)
A4: Electronics | B4: =SUM(StoreData!B2:B7)
A5: HomeGoods | B5: =SUM(StoreData!C2:C7)
A6: Clothing | B6: =SUM(StoreData!D2:D7)
A7: GRAND TOTAL | B7: =SUM(B4:B6)
B9: Total Sales
A10: Electronics | B10: 890000
A11: HomeGoods | B11: 566000
A12: Clothing | B12: 419000

Sheet 2.2.2_Forecast
A1: Electronics Sales Forecast — Linear Trendline Analysis
A3: Month | B3: Period (x) | C3: Electronics Sales
A4: January | B4: 1 | C4: 120000
A5: February | B5: 2 | C5: 135000
A6: March | B6: 3 | C6: 150000
A7: April | B7: 4 | C7: 160000
A8: May | B8: 5 | C8: 170000
A9: June | B9: 6 | C9: 155000
A10: July (Forecast) | B10: 7 | C10: 177333
A11: August (Forecast) | B11: 8 | C11: 185619
A12: Trendline Analysis:
A13: Linear Equation: y = 8285.71x + 119333.33
A14: R² Value: 0.7356
A15: Slope: 8285.71 (average monthly increase in Electronics sales)
A16: July Forecast (x=7): £177,333
A17: August Forecast (x=8): £185,619

Sheet 2.2.3_Accountants_Report
A1: Accountant's Detailed Report — Sales, Expenses & Profit Analysis
A3: Month | B3: Product | C3: Sales | D3: Expenses | E3: Profit | F3: Low Profit Flag
A4: January | B4: Electronics | C4: =StoreData!B2 | D4: =StoreData!E2 | E4: =C4-D4 | F4: =IF(E4<20000,"⚠ LOW PROFIT","OK")
A5: January | B5: HomeGoods | C5: =StoreData!C2 | D5: =StoreData!F2 | E5: =C5-D5 | F5: =IF(E5<20000,"⚠ LOW PROFIT","OK")
A6: January | B6: Clothing | C6: =StoreData!D2 | D6: =StoreData!G2 | E6: =C6-D6 | F6: =IF(E6<20000,"⚠ LOW PROFIT","OK")
A7: February | B7: Electronics | C7: =StoreData!B3 | D7: =StoreData!E3 | E7: =C7-D7 | F7: =IF(E7<20000,"⚠ LOW PROFIT","OK")
A8: February | B8: HomeGoods | C8: =StoreData!C3 | D8: =StoreData!F3 | E8: =C8-D8 | F8: =IF(E8<20000,"⚠ LOW PROFIT","OK")
A9: February | B9: Clothing | C9: =StoreData!D3 | D9: =StoreData!G3 | E9: =C9-D9 | F9: =IF(E9<20000,"⚠ LOW PROFIT","OK")
A10: March | B10: Electronics | C10: =StoreData!B4 | D10: =StoreData!E4 | E10: =C10-D10 | F10: =IF(E10<20000,"⚠ LOW PROFIT","OK")
A11: March | B11: HomeGoods | C11: =StoreData!C4 | D11: =StoreData!F4 | E11: =C11-D11 | F11: =IF(E11<20000,"⚠ LOW PROFIT","OK")
A12: March | B12: Clothing | C12: =StoreData!D4 | D12: =StoreData!G4 | E12: =C12-D12 | F12: =IF(E12<20000,"⚠ LOW PROFIT","OK")
A13: April | B13: Electronics | C13: =StoreData!B5 | D13: =StoreData!E5 | E13: =C13-D13 | F13: =IF(E13<20000,"⚠ LOW PROFIT","OK")
A14: April | B14: HomeGoods | C14: =StoreData!C5 | D14: =StoreData!F5 | E14: =C14-D14 | F14: =IF(E14<20000,"⚠ LOW PROFIT","OK")
A15: April | B15: Clothing | C15: =StoreData!D5 | D15: =StoreData!G5 | E15: =C15-D15 | F15: =IF(E15<20000,"⚠ LOW PROFIT","OK")
A16: May | B16: Electronics | C16: =StoreData!B6 | D16: =StoreData!E6 | E16: =C16-D16 | F16: =IF(E16<20000,"⚠ LOW PROFIT","OK")
A17: May | B17: HomeGoods | C17: =StoreData!C6 | D17: =StoreData!F6 | E17: =C17-D17 | F17: =IF(E17<20000,"⚠ LOW PROFIT","OK")
A18: May | B18: Clothing | C18: =StoreData!D6 | D18: =StoreData!G6 | E18: =C18-D18 | F18: =IF(E18<20000,"⚠ LOW PROFIT","OK")
A19: June | B19: Electronics | C19: =StoreData!B7 | D19: =StoreData!E7 | E19: =C19-D19 | F19: =IF(E19<20000,"⚠ LOW PROFIT","OK")
A20: June | B20: HomeGoods | C20: =StoreData!C7 | D20: =StoreData!F7 | E20: =C20-D20 | F20: =IF(E20<20000,"⚠ LOW PROFIT","OK")
A21: June | B21: Clothing | C21: =StoreData!D7 | D21: =StoreData!G7 | E21: =C21-D21 | F21: =IF(E21<20000,"⚠ LOW PROFIT","OK")
A22: Summary by Product (SUMIF)
A23: Product | B23: Total Sales | C23: Total Expenses | D23: Total Profit
A24: Electronics | B24: =SUMIF($B$4:$B$21,A24,$C$4:$C$21) | C24: =SUMIF($B$4:$B$21,A24,$D$4:$D$21) | D24: =B24-C24
A25: HomeGoods | B25: =SUMIF($B$4:$B$21,A25,$C$4:$C$21) | C25: =SUMIF($B$4:$B$21,A25,$D$4:$D$21) | D25: =B25-C25
A26: Clothing | B26: =SUMIF($B$4:$B$21,A26,$C$4:$C$21) | C26: =SUMIF($B$4:$B$21,A26,$D$4:$D$21) | D26: =B26-C26
